replit_river/__init__.py
replit_river/client.py
replit_river/client_session.py
replit_river/client_transport.py
replit_river/common_session.py
replit_river/error_schema.py
replit_river/message_buffer.py
replit_river/messages.py
replit_river/py.typed
replit_river/rate_limiter.py
replit_river/rpc.py
replit_river/seq_manager.py
replit_river/server.py
replit_river/server_session.py
replit_river/server_transport.py
replit_river/session.py
replit_river/task_manager.py
replit_river/transport_options.py
replit_river/websocket_wrapper.py
replit_river/codegen/__init__.py
replit_river/codegen/__main__.py
replit_river/codegen/client.py
replit_river/codegen/format.py
replit_river/codegen/run.py
replit_river/codegen/schema.py
replit_river/codegen/server.py
replit_river/codegen/typing.py
replit_river/v2/__init__.py
replit_river/v2/client.py
replit_river/v2/client_transport.py
replit_river/v2/session.py
replit_river-0.17.13.dist-info/METADATA
replit_river-0.17.13.dist-info/WHEEL
replit_river-0.17.13.dist-info/licenses/LICENSE
replit_river-0.17.13.dist-info/RECORD
